team_plus/__init__.py
team_plus/t_plus.py
team_plus-0.4.0.dist-info/METADATA
team_plus-0.4.0.dist-info/WHEEL
team_plus-0.4.0.dist-info/entry_points.txt
team_plus-0.4.0.dist-info/top_level.txt
team_plus-0.4.0.dist-info/RECORD
